Metadata-Version: 2.1
Name: fastSource
Version: 0.1
Summary: Automatic classification of Source Metadata.
Home-page: https://github.com/zheminzhou/fastSource
Author: Zhemin Zhou
Author-email: zhemin.zhou@warwick.ac.uk
License: UNKNOWN
Keywords: bioinformatics,microbial,genomics,metadata,machine learning,text classification
Platform: UNKNOWN
Classifier: Development Status :: 5 - Production/Stable
Classifier: Programming Language :: Python :: 3.5
Classifier: Programming Language :: Python :: 3.6
Classifier: Programming Language :: Python :: 3.7
Classifier: Programming Language :: Python :: 3.8
Classifier: License :: OSI Approved :: GNU General Public License v3 (GPLv3)
Classifier: Operating System :: OS Independent
